{
  "Ajustes": {"Fuerza":-2,"Constitución":2},
  "Tamaño": "Pequeño",
  "Subtipo": "gnomo",
  "Clase predilecta":"Bardo",
  "Especial":[
    "Habilidad Racial:Artesanía",
    "Habilidad Racial:Escuchar",
    "Aptitud Sortílega:Hablar con los animales",
    "Aptitud Sortílega:Luces danzantes",
    "Aptitud Sortílega:Prestidigitación",
    "Aptitud Sortílega:Sonido fantasma"
  ],
  "Velocidad": "20'",
  "Idiomas_Automáticos": ["Común","Gnomo"],
  "Idiomas_Adicionales": ["Dracónico","Élfico","Enano","Gigante","Orco","Trasgo"],
  "Aptitudes":{
    "Habilidad Racial:Artesanía":{"Tipo":"u", "Valor":2},
    "Habilidad Racial:Escuchar":{"Tipo":"u", "Valor":2},
    "Aptitud Sortílega:Hablar con los animales":{"Tipo":"u"},
    "Aptitud Sortílega:Luces danzantes":{"Tipo":"u", "Reqs":{"Carisma":10}},
    "Aptitud Sortílega:Prestidigitación":{"Tipo":"u", "Reqs":{"Carisma":10}},
    "Aptitud Sortílega:Sonido fantasma":{"Tipo":"u", "Reqs":{"Carisma":10}}
  }
}